Metadata-Version: 1.0
Name: pp-gaussian-binomial
Version: 1.2
Summary: Gaussian and Binomial distributions
Home-page: UNKNOWN
Author: Prajwala D
Author-email: UNKNOWN
License: UNKNOWN
Platform: UNKNOWN
